keba_kecontact/__init__.py
keba_kecontact/chargingstation.py
keba_kecontact/connection.py
keba_kecontact/const.py
keba_kecontact/emulator.py
keba_kecontact_spali-3.0.3.dist-info/LICENSE
keba_kecontact_spali-3.0.3.dist-info/METADATA
keba_kecontact_spali-3.0.3.dist-info/WHEEL
keba_kecontact_spali-3.0.3.dist-info/top_level.txt
keba_kecontact_spali-3.0.3.dist-info/RECORD
