Metadata-Version: 2.1
Name: keba-kecontact-spali
Version: 3.0.3
Summary: A python library to communicate with the KEBA charging stations via udp
Home-page: https://github.com/dannerph/keba-kecontact
Author: Philipp Danner
Author-email: philipp@danner-web.de
Classifier: Programming Language :: Python :: 3
Classifier: License :: OSI Approved :: MIT License
Classifier: Operating System :: OS Independent
License-File: LICENSE
Requires-Dist: asyncio-dgram >=2.1.1
Requires-Dist: netifaces >=0.11.0
